{
  "id": "deploy-us10-dashboard",
  "title": "US-10 Dashboard metrics",
  "base": "https://crucible-zaag.onrender.com",
  "page": "/app/slice-04-honest-dashboard.dc.html",
  "waitText": "Outcomes",
  "dwellMs": 2000,
  "apiRoutes": [
    "/metrics",
    "/spend/current-month",
    "/halt",
    "/health"
  ],
  "steps": [
    {
      "action": "wait",
      "ms": 2600
    },
    {
      "action": "scroll",
      "dy": 200,
      "ms": 1900
    },
    {
      "action": "wait",
      "ms": 2000
    },
    {
      "action": "scroll",
      "dy": 220,
      "ms": 1900
    },
    {
      "action": "wait",
      "ms": 2000
    },
    {
      "action": "scroll",
      "dy": 220,
      "ms": 1900
    },
    {
      "action": "wait",
      "ms": 1800
    },
    {
      "action": "scrollTop",
      "ms": 1900
    }
  ]
}